snowdrop_adjudicators/__init__.py
snowdrop_adjudicators/adjudicators/__init__.py
snowdrop_adjudicators/adjudicators/adjudicator.py
snowdrop_adjudicators/adjudicators/schrodinger.py
snowdrop_adjudicators/adjudicators/simulated_annealing.py
snowdrop_adjudicators/schrodinger/__init__.py
snowdrop_adjudicators/schrodinger/advantage2.1.3.txt
snowdrop_adjudicators/schrodinger/schrodinger_functions.py
snowdrop_adjudicators/schrodinger/sparse_matrices.py
snowdrop_adjudicators/tests/__init__.py
snowdrop_adjudicators/tests/conftest.py
snowdrop_adjudicators/tests/test_adjudicators/__init__.py
snowdrop_adjudicators/tests/test_adjudicators/test_schrodinger.py
snowdrop_adjudicators/tests/test_adjudicators/test_simulated_annealing.py
snowdrop_adjudicators-0.1.0.dist-info/licenses/LICENSE
snowdrop_adjudicators-0.1.0.dist-info/METADATA
snowdrop_adjudicators-0.1.0.dist-info/WHEEL
snowdrop_adjudicators-0.1.0.dist-info/RECORD
