Metadata-Version: 2.4
Name: snowdrop-adjudicators
Version: 0.1.0
Summary: Two public adjudicators for the Tangled game
License: MIT
License-File: LICENSE
Author: Geordie Rose
Author-email: greatblueheron@users.noreply.github.com
Requires-Python: >=3.11,<3.14
Classifier: License :: OSI Approved :: MIT License
Classifier: Programming Language :: Python :: 3
Classifier: Programming Language :: Python :: 3.11
Classifier: Programming Language :: Python :: 3.12
Classifier: Programming Language :: Python :: 3.13
Requires-Dist: dwave-neal (>=0.6.0)
Requires-Dist: scipy (>=1.16.3)
Requires-Dist: snowdrop-tangled-game-engine (>=1.1.0)
Project-URL: Bug Tracker, https://github.com/snowdropquantum/snowdrop-adjudicators/issues
Project-URL: Documentation, https://github.com/snowdropquantum/snowdrop-adjudicators
Project-URL: Homepage, https://github.com/snowdropquantum/snowdrop-adjudicators
Project-URL: Repository, https://github.com/snowdropquantum/snowdrop-adjudicators
